docs/Makefile
docs/make.bat
docs/requirements.txt
docs/source/api.rst
docs/source/changelog.rst
docs/source/chat.rst
docs/source/chunking-for-llms.rst
docs/source/conf.py
docs/source/contributing.rst
docs/source/data-labelling-llms.rst
docs/source/dependencies.rst
docs/source/embed-sentences.rst
docs/source/further-pretrain-mlms.rst
docs/source/index.rst
docs/source/installation.rst
docs/source/license.rst
docs/source/llm-inference.rst
docs/source/mimick-a-model.rst
docs/source/pretrain-mlms.rst
docs/source/reranker.rst
docs/source/semantic-search.rst
docs/source/train-text-classifiers.rst
docs/source/_includes/official_links.html
docs/source/_static/apple-touch-icon.png
docs/source/_static/chat-advanced.png
docs/source/_static/chat.png
docs/source/_static/custom.css
docs/source/_static/favicon-96x96.png
docs/source/_static/favicon.ico
docs/source/_static/favicon.svg
docs/source/_static/logo.png
docs/source/_static/tasks.svg
env/bin/vba_extract.py
langformers/LICENSE
langformers/__init__.py
langformers/_version.py
langformers/factory.py
langformers/chunkers/__init__.py
langformers/chunkers/fixed_size_chunker.py
langformers/chunkers/recursive_chunker.py
langformers/chunkers/semantic_chunker.py
langformers/classifiers/__init__.py
langformers/classifiers/huggingface_classifier.py
langformers/classifiers/load_classifier.py
langformers/classifiers/customs/__init__.py
langformers/classifiers/customs/custom_classification_dataset.py
langformers/classifiers/customs/custom_classification_model.py
langformers/classifiers/customs/custom_classification_trainer.py
langformers/commons/__init__.py
langformers/commons/device.py
langformers/commons/generate_prompt.py
langformers/commons/mean_pooler.py
langformers/commons/print_message.py
langformers/commons/prompts.py
langformers/commons/rand_name.py
langformers/embedders/__init__.py
langformers/embedders/huggingface_embedder.py
langformers/generators/__init__.py
langformers/generators/huggingface_generator.py
langformers-0.5.0.dist-info/licenses/LICENSE
langformers-0.5.0.dist-info/METADATA
langformers-0.5.0.dist-info/WHEEL
langformers-0.5.0.dist-info/top_level.txt
langformers-0.5.0.dist-info/RECORD
