Metadata-Version: 2.4
Name: langformers
Version: 0.5.0
Summary: 🚀 Unified NLP Pipelines for Language Models
Author-email: Rabindra Lamsal <mail@langformers.com>
License-Expression: Apache-2.0
Project-URL: Homepage, https://github.com/langformers/langformers
Project-URL: Documentation, https://langformers.com
Project-URL: Repository, https://github.com/langformers/langformers
Project-URL: Issues, https://github.com/langformers/langformers/issues
Classifier: Programming Language :: Python :: 3
Classifier: Programming Language :: Python :: 3.10
Classifier: Operating System :: OS Independent
Classifier: Topic :: Scientific/Engineering :: Artificial Intelligence
Requires-Python: >=3.10
License-File: LICENSE
Requires-Dist: transformers>=4.51.0
Requires-Dist: tokenizers>=0.21.1
Requires-Dist: datasets>=3.5.0
Requires-Dist: torch>=2.6.0
Requires-Dist: accelerate>=1.6.0
Requires-Dist: safetensors>=0.5.3
Requires-Dist: scikit-learn>=1.6.1
Requires-Dist: ollama>=0.4.7
Requires-Dist: fastapi>=0.115.9
Requires-Dist: uvicorn>=0.34.0
Requires-Dist: pandas
Requires-Dist: numpy
Requires-Dist: requests>=2.32.3
Requires-Dist: tqdm>=4.67.1
Requires-Dist: colorama>=0.4.6
Requires-Dist: tensorboard>=2.19.0
Provides-Extra: faiss
Requires-Dist: faiss-cpu; extra == "faiss"
Provides-Extra: chromadb
Requires-Dist: chromadb; extra == "chromadb"
Provides-Extra: pinecone
Requires-Dist: pinecone-client; extra == "pinecone"
Provides-Extra: all
Requires-Dist: faiss-cpu; extra == "all"
Requires-Dist: chromadb; extra == "all"
Requires-Dist: pinecone; extra == "all"
Dynamic: license-file
